<annotation><filename>4</filename><folder>example_folder</folder><source><sourceImage>The MIT-CSAIL database of objects and scenes</sourceImage><sourceAnnotation>LabelMe Webtool</sourceAnnotation></source><object><name>groundplane</name><deleted>0</deleted><verified>0</verified><parts><hasparts></hasparts><ispartof></ispartof></parts><date>26-Aug-2015 04:44:19</date><id>0</id><type>plane</type><plane><lines><vp_line><x1>0.017973856209150325</x1><y1>0.012745098039215658</y1><x2>0.35751633986928105</x2><y2>0.07705882352941176</y2><label>1</label></vp_line><vp_line><x1>0.8316993464052288</x1><y1>0.5975490196078431</y1><x2>0.4065359477124183</x2><y2>0.7656862745098039</y2><label>1</label></vp_line><vp_line><x1>0.9003267973856209</x1><y1>0.012745098039215658</y1><x2>0.3581699346405229</x2><y2>0.0746078431372549</y2><label>2</label></vp_line><vp_line><x1>0.6683006535947712</x1><y1>0.6710784313725489</y1><x2>0.1980392156862745</x2><y2>0.5696078431372549</y2><label>2</label></vp_line></lines><op_points>0.3888888888888889 0.5416666666666666</op_points><plane_matrix>0.6095741987228394 0.14736498892307281 -0.7789113521575928 0 -0.7798346281051636 0.14415521919727325 -0.6091610789299011 0 0.02251512184739113 0.9787509441375732 0.20279362797737122 0 0.08884524554014206 -0.33222779631614685 0.3880724310874939 1 </plane_matrix><focal_length>417.61251930161416</focal_length></plane></object><imagesize><nrows></nrows><ncols></ncols></imagesize></annotation>