<annotation><filename>79</filename><folder>example_folder</folder><source><sourceImage>The MIT-CSAIL database of objects and scenes</sourceImage><sourceAnnotation>LabelMe Webtool</sourceAnnotation></source><object><name>groundplane</name><deleted>0</deleted><verified>0</verified><parts><hasparts></hasparts><ispartof></ispartof></parts><date>26-Aug-2015 13:07:52</date><id>0</id><type>plane</type><plane><lines><vp_line><x1>0.2889907407407407</x1><y1>0.1376379629629629</y1><x2>0.6772506172839505</x2><y2>0.26802666666666664</y2><label>1</label></vp_line><vp_line><x1>0.4914475308641975</x1><y1>1.0011814814814812</y1><x2>0.5988802469135801</x2><y2>0.8948916666666664</y2><label>1</label></vp_line><vp_line><x1>0.9928117283950617</x1><y1>0.25719814814814806</y1><x2>0.8685765432098767</x2><y2>0.2596979629629628</y2><label>2</label></vp_line><vp_line><x1>0.6447685185185185</x1><y1>0.6618805555555551</y1><x2>0.3762061728395061</x2><y2>0.6418453703703703</y2><label>2</label></vp_line></lines><op_points>0.6699814814814815 0.6718333333333334</op_points><plane_matrix>0.3565129041671753 0.07415150851011276 -0.9313431978225708 0 -0.9332619905471802 0.046337272971868515 -0.35619500279426575 0 0.016743507236242294 0.9961753487586975 0.08572261780500412 0 0.6868814826011658 -0.26892808079719543 0.28753820061683655 1 </plane_matrix><focal_length>473.7381647526996</focal_length></plane></object><imagesize><nrows></nrows><ncols></ncols></imagesize></annotation>