<annotation><filename>173</filename><folder>example_folder</folder><source><sourceImage>The MIT-CSAIL database of objects and scenes</sourceImage><sourceAnnotation>LabelMe Webtool</sourceAnnotation></source><object><name>groundplane</name><deleted>0</deleted><verified>0</verified><parts><hasparts/><ispartof/></parts><date>25-Aug-2015 18:30:22</date><id>0</id><type>plane</type><plane><lines><vp_line><x1>0.0030864197530864196</x1><y1>0.23333333333333334</y1><x2>0.4266721945826423</x2><y2>0.275679012345679</y2><label>1</label></vp_line><vp_line><x1>0.007716049382716049</x1><y1>0.9127572016460906</y1><x2>0.42006172839506173</x2><y2>0.813374485596708</y2><label>1</label></vp_line><vp_line><x1>0.9891975308641975</x1><y1>0.021399176954732525</y1><x2>0.4827160493827161</x2><y2>0.11930041152263371</y2><label>2</label></vp_line><vp_line><x1>0.9050810761009765</x1><y1>0.9023770038695412</y1><x2>0.36414225170444076</x2><y2>0.6483354830784349</y2><label>2</label></vp_line></lines><op_points>0.3591767650907436 0.7705619085547402</op_points><plane_matrix>0.7896543741226196 0.026531865820288658 -0.6129780411720276 0 -0.6080605387687683 0.10659658163785934 -0.7867016792297363 0 0.044468700885772705 0.9939501881599426 0.10030743479728699 0 -0.3016357421875 -0.307531476020813 0.3996797204017639 1 </plane_matrix><focal_length>1191.4445813322875</focal_length></plane></object><imagesize><nrows></nrows><ncols></ncols></imagesize></annotation>