<annotation><filename>54</filename><folder>example_folder</folder><source><sourceImage>The MIT-CSAIL database of objects and scenes</sourceImage><sourceAnnotation>LabelMe Webtool</sourceAnnotation></source><object><name>groundplane</name><deleted>0</deleted><verified>0</verified><parts><hasparts/><ispartof/></parts><date>26-Aug-2015 16:14:52</date><id>0</id><type>plane</type><plane><lines><vp_line><x1>0.07299546142208775</x1><y1>-0.0012096774193548273</y1><x2>0.2804841149773071</x2><y2>0.02274193548387097</y2><label>1</label></vp_line><vp_line><x1>0.45121028744326785</x1><y1>0.757258064516129</y1><x2>0.8992435703479577</x2><y2>0.4754032258064515</y2><label>1</label></vp_line><vp_line><x1>0.6647416501803795</x1><y1>0.07623035566583955</y1><x2>0.5011859216804376</x2><y2>0.08932588916459884</y2><label>2</label></vp_line><vp_line><x1>0.4595310136157337</x1><y1>0.755241935483871</y1><x2>0.005446293494705113</x2><y2>0.5419354838709678</y2><label>2</label></vp_line></lines><op_points>0.4982598481322006 0.4593672456575683</op_points><plane_matrix>0.6389175653457642 0.18231862783432007 -0.7473582029342651 0 -0.7521898150444031 0.14079099893569946 -0.6437300443649292 0 -0.012142670340836048 0.9734456539154053 0.22709205746650696 0 0.11163977533578873 -0.2945207953453064 0.39108824729919434 1 </plane_matrix><focal_length>426.3841565065825</focal_length></plane></object><imagesize><nrows></nrows><ncols></ncols></imagesize></annotation>